{
  "runs_checked": 4,
  "num_findings_total": 4,
  "runs": [
    {
      "run_dir": "C:\\Users\\micha\\zGTFinal\\outputs\\final_local_fd001_fulltopo",
      "tem_metrics_path": "C:\\Users\\micha\\zGTFinal\\outputs\\final_local_fd001_fulltopo\\tem_metrics_fd001.json",
      "audit_path": "C:\\Users\\micha\\zGTFinal\\outputs\\final_local_fd001_fulltopo\\audit_fd001.json",
      "cache_path": "C:\\Users\\micha\\zGTFinal\\outputs\\final_local_fd001_fulltopo\\audit_cache_fd001.npz",
      "use_conditional_calibration": true,
      "config": {
        "pvalue_safety_margin": 0.02,
        "calibration_bins": 8,
        "calibration_min_bin_size": 128,
        "topology_level": "full",
        "surface_topology_scope": "all"
      },
      "integrity": {
        "has_nan": false,
        "coverage_in_range": true,
        "surface_topology_ok": true
      },
      "blocks": {
        "global": {
          "n": 10196,
          "status": "ok",
          "mean_p": 0.5791974862647338,
          "checks": [
            {
              "a": 0.1,
              "frac_le_a": 0.07502942330325618,
              "bound": 0.11,
              "pass": true
            },
            {
              "a": 0.2,
              "frac_le_a": 0.14456649666535895,
              "bound": 0.21188410096009197,
              "pass": true
            },
            {
              "a": 0.5,
              "frac_le_a": 0.3928991761475088,
              "bound": 0.514855126200115,
              "pass": true
            }
          ]
        },
        "healthy_prefix": {
          "n": 7069,
          "status": "ok",
          "mean_p": 0.5903964293047128,
          "checks": [
            {
              "a": 0.1,
              "frac_le_a": 0.06068750884142029,
              "bound": 0.11070442931236323,
              "pass": true
            },
            {
              "a": 0.2,
              "frac_le_a": 0.1161408968736738,
              "bound": 0.2142725724164843,
              "pass": true
            },
            {
              "a": 0.5,
              "frac_le_a": 0.37940302730230585,
              "bound": 0.5178407155206054,
              "pass": true
            }
          ]
        },
        "low_rul": {
          "n": 332,
          "status": "fail",
          "mean_p": 0.46599391328306994,
          "checks": [
            {
              "a": 0.1,
              "frac_le_a": 0.20783132530120482,
              "bound": 0.14939391699536067,
              "pass": false
            },
            {
              "a": 0.2,
              "frac_le_a": 0.3433734939759036,
              "bound": 0.26585855599381425,
              "pass": false
            },
            {
              "a": 0.5,
              "frac_le_a": 0.5331325301204819,
              "bound": 0.5823231949922678,
              "pass": true
            }
          ]
        },
        "mid_rul": {
          "n": 1703,
          "status": "ok",
          "mean_p": 0.550219485486661,
          "checks": [
            {
              "a": 0.1,
              "frac_le_a": 0.1092190252495596,
              "bound": 0.12180897152526954,
              "pass": true
            },
            {
              "a": 0.2,
              "frac_le_a": 0.2172636523781562,
              "bound": 0.2290786287003594,
              "pass": true
            },
            {
              "a": 0.5,
              "frac_le_a": 0.4368761009982384,
              "bound": 0.5363482858754492,
              "pass": true
            }
          ]
        },
        "high_rul": {
          "n": 8161,
          "status": "ok",
          "mean_p": 0.5898497496583093,
          "checks": [
            {
              "a": 0.1,
              "frac_le_a": 0.062492341624800885,
              "bound": 0.11,
              "pass": true
            },
            {
              "a": 0.2,
              "frac_le_a": 0.12130866315402525,
              "bound": 0.21328340937363874,
              "pass": true
            },
            {
              "a": 0.5,
              "frac_le_a": 0.3780173998284524,
              "bound": 0.5166042617170484,
              "pass": true
            }
          ]
        },
        "early_time": {
          "n": 3424,
          "status": "ok",
          "mean_p": 0.6354040107538933,
          "checks": [
            {
              "a": 0.1,
              "frac_le_a": 0.04672897196261682,
              "bound": 0.11538068335805493,
              "pass": true
            },
            {
              "a": 0.2,
              "frac_le_a": 0.09258177570093458,
              "bound": 0.2205075778107399,
              "pass": true
            },
            {
              "a": 0.5,
              "frac_le_a": 0.32389018691588783,
              "bound": 0.5256344722634249,
              "pass": true
            }
          ]
        },
        "mid_time": {
          "n": 3362,
          "status": "ok",
          "mean_p": 0.5886848382423082,
          "checks": [
            {
              "a": 0.1,
              "frac_le_a": 0.07674003569303986,
              "bound": 0.11552185617238764,
              "pass": true
            },
            {
              "a": 0.2,
              "frac_le_a": 0.13027959547888163,
              "bound": 0.2206958082298502,
              "pass": true
            },
            {
              "a": 0.5,
              "frac_le_a": 0.37031528851873885,
              "bound": 0.5258697602873127,
              "pass": true
            }
          ]
        },
        "late_time": {
          "n": 3410,
          "status": "ok",
          "mean_p": 0.5134063961769075,
          "checks": [
            {
              "a": 0.1,
              "frac_le_a": 0.10175953079178886,
              "bound": 0.1154122242681417,
              "pass": true
            },
            {
              "a": 0.2,
              "frac_le_a": 0.21085043988269794,
              "bound": 0.22054963235752226,
              "pass": true
            },
            {
              "a": 0.5,
              "frac_le_a": 0.4844574780058651,
              "bound": 0.5256870404469028,
              "pass": true
            }
          ]
        }
      },
      "failed_blocks": [
        "low_rul"
      ],
      "num_findings": 1,
      "findings": [
        {
          "severity": "medium",
          "type": "regime_superuniformity_failure",
          "message": "Failed blocks: ['low_rul']"
        }
      ]
    },
    {
      "run_dir": "C:\\Users\\micha\\zGTFinal\\outputs\\final_local_fd002_fulltopo",
      "tem_metrics_path": "C:\\Users\\micha\\zGTFinal\\outputs\\final_local_fd002_fulltopo\\tem_metrics_fd002.json",
      "audit_path": "C:\\Users\\micha\\zGTFinal\\outputs\\final_local_fd002_fulltopo\\audit_fd002.json",
      "cache_path": "C:\\Users\\micha\\zGTFinal\\outputs\\final_local_fd002_fulltopo\\audit_cache_fd002.npz",
      "use_conditional_calibration": true,
      "config": {
        "pvalue_safety_margin": 0.02,
        "calibration_bins": 8,
        "calibration_min_bin_size": 128,
        "topology_level": "full",
        "surface_topology_scope": "all"
      },
      "integrity": {
        "has_nan": false,
        "coverage_in_range": true,
        "surface_topology_ok": true
      },
      "blocks": {
        "global": {
          "n": 26511,
          "status": "ok",
          "mean_p": 0.5147970768235134,
          "checks": [
            {
              "a": 0.1,
              "frac_le_a": 0.08554939459092452,
              "bound": 0.11,
              "pass": true
            },
            {
              "a": 0.2,
              "frac_le_a": 0.19365546376975595,
              "bound": 0.21000000000000002,
              "pass": true
            },
            {
              "a": 0.5,
              "frac_le_a": 0.4984346120478292,
              "bound": 0.51,
              "pass": true
            }
          ]
        },
        "healthy_prefix": {
          "n": 17850,
          "status": "ok",
          "mean_p": 0.5266814213694639,
          "checks": [
            {
              "a": 0.1,
              "frac_le_a": 0.0773109243697479,
              "bound": 0.11,
              "pass": true
            },
            {
              "a": 0.2,
              "frac_le_a": 0.1785434173669468,
              "bound": 0.21000000000000002,
              "pass": true
            },
            {
              "a": 0.5,
              "frac_le_a": 0.4788795518207283,
              "bound": 0.5112272178284768,
              "pass": true
            }
          ]
        },
        "low_rul": {
          "n": 1087,
          "status": "fail",
          "mean_p": 0.4407616356735999,
          "checks": [
            {
              "a": 0.1,
              "frac_le_a": 0.12879484820607176,
              "bound": 0.12729780564793208,
              "pass": false
            },
            {
              "a": 0.2,
              "frac_le_a": 0.23919043238270468,
              "bound": 0.2363970741972428,
              "pass": false
            },
            {
              "a": 0.5,
              "frac_le_a": 0.6264949402023919,
              "bound": 0.5454963427465535,
              "pass": false
            }
          ]
        },
        "mid_rul": {
          "n": 4623,
          "status": "fail",
          "mean_p": 0.4834085951574149,
          "checks": [
            {
              "a": 0.1,
              "frac_le_a": 0.12113346311918667,
              "bound": 0.1132367255018634,
              "pass": false
            },
            {
              "a": 0.2,
              "frac_le_a": 0.26779147739563053,
              "bound": 0.21764896733581787,
              "pass": false
            },
            {
              "a": 0.5,
              "frac_le_a": 0.5425048669695003,
              "bound": 0.5220612091697723,
              "pass": false
            }
          ]
        },
        "high_rul": {
          "n": 20801,
          "status": "ok",
          "mean_p": 0.5256420109743873,
          "checks": [
            {
              "a": 0.1,
              "frac_le_a": 0.07538099129849526,
              "bound": 0.11,
              "pass": true
            },
            {
              "a": 0.2,
              "frac_le_a": 0.1747992884957454,
              "bound": 0.21000000000000002,
              "pass": true
            },
            {
              "a": 0.5,
              "frac_le_a": 0.4819479832700351,
              "bound": 0.5104003786731252,
              "pass": true
            }
          ]
        },
        "early_time": {
          "n": 8892,
          "status": "ok",
          "mean_p": 0.5617402582902017,
          "checks": [
            {
              "a": 0.1,
              "frac_le_a": 0.05004498425551057,
              "bound": 0.11,
              "pass": true
            },
            {
              "a": 0.2,
              "frac_le_a": 0.1424876293297346,
              "bound": 0.21272569525951557,
              "pass": true
            },
            {
              "a": 0.5,
              "frac_le_a": 0.4290373369320738,
              "bound": 0.5159071190743945,
              "pass": true
            }
          ]
        },
        "mid_time": {
          "n": 8750,
          "status": "fail",
          "mean_p": 0.47316940521126566,
          "checks": [
            {
              "a": 0.1,
              "frac_le_a": 0.108,
              "bound": 0.11,
              "pass": true
            },
            {
              "a": 0.2,
              "frac_le_a": 0.23314285714285715,
              "bound": 0.21282853961179637,
              "pass": false
            },
            {
              "a": 0.5,
              "frac_le_a": 0.5552,
              "bound": 0.5160356745147454,
              "pass": false
            }
          ]
        },
        "late_time": {
          "n": 8869,
          "status": "ok",
          "mean_p": 0.5088012889111643,
          "checks": [
            {
              "a": 0.1,
              "frac_le_a": 0.09899650467921975,
              "bound": 0.11,
              "pass": true
            },
            {
              "a": 0.2,
              "frac_le_a": 0.20599842146803474,
              "bound": 0.21274218536423714,
              "pass": true
            },
            {
              "a": 0.5,
              "frac_le_a": 0.5120081181643928,
              "bound": 0.5159277317052964,
              "pass": true
            }
          ]
        }
      },
      "failed_blocks": [
        "low_rul",
        "mid_rul",
        "mid_time"
      ],
      "num_findings": 1,
      "findings": [
        {
          "severity": "medium",
          "type": "regime_superuniformity_failure",
          "message": "Failed blocks: ['low_rul', 'mid_rul', 'mid_time']"
        }
      ]
    },
    {
      "run_dir": "C:\\Users\\micha\\zGTFinal\\outputs\\final_local_fd003_fulltopo",
      "tem_metrics_path": "C:\\Users\\micha\\zGTFinal\\outputs\\final_local_fd003_fulltopo\\tem_metrics_fd003.json",
      "audit_path": "C:\\Users\\micha\\zGTFinal\\outputs\\final_local_fd003_fulltopo\\audit_fd003.json",
      "cache_path": "C:\\Users\\micha\\zGTFinal\\outputs\\final_local_fd003_fulltopo\\audit_cache_fd003.npz",
      "use_conditional_calibration": true,
      "config": {
        "pvalue_safety_margin": 0.02,
        "calibration_bins": 8,
        "calibration_min_bin_size": 128,
        "topology_level": "full",
        "surface_topology_scope": "all"
      },
      "integrity": {
        "has_nan": false,
        "coverage_in_range": true,
        "surface_topology_ok": true
      },
      "blocks": {
        "global": {
          "n": 13696,
          "status": "ok",
          "mean_p": 0.5824472968611073,
          "checks": [
            {
              "a": 0.1,
              "frac_le_a": 0.06549357476635514,
              "bound": 0.11,
              "pass": true
            },
            {
              "a": 0.2,
              "frac_le_a": 0.16508469626168223,
              "bound": 0.21025378890536997,
              "pass": true
            },
            {
              "a": 0.5,
              "frac_le_a": 0.4107038551401869,
              "bound": 0.5128172361317125,
              "pass": true
            }
          ]
        },
        "healthy_prefix": {
          "n": 10457,
          "status": "ok",
          "mean_p": 0.6288289018918152,
          "checks": [
            {
              "a": 0.1,
              "frac_le_a": 0.032131586497083295,
              "bound": 0.11,
              "pass": true
            },
            {
              "a": 0.2,
              "frac_le_a": 0.12527493544993784,
              "bound": 0.21173485403714995,
              "pass": true
            },
            {
              "a": 0.5,
              "frac_le_a": 0.3577507889452042,
              "bound": 0.5146685675464374,
              "pass": true
            }
          ]
        },
        "low_rul": {
          "n": 291,
          "status": "fail",
          "mean_p": 0.31837198518716137,
          "checks": [
            {
              "a": 0.1,
              "frac_le_a": 0.281786941580756,
              "bound": 0.15275893435844945,
              "pass": false
            },
            {
              "a": 0.2,
              "frac_le_a": 0.422680412371134,
              "bound": 0.27034524581126596,
              "pass": false
            },
            {
              "a": 0.5,
              "frac_le_a": 0.7731958762886598,
              "bound": 0.5879315572640824,
              "pass": false
            }
          ]
        },
        "mid_rul": {
          "n": 1736,
          "status": "fail",
          "mean_p": 0.43494250278967944,
          "checks": [
            {
              "a": 0.1,
              "frac_le_a": 0.2574884792626728,
              "bound": 0.12160069123317938,
              "pass": false
            },
            {
              "a": 0.2,
              "frac_le_a": 0.3824884792626728,
              "bound": 0.22880092164423918,
              "pass": false
            },
            {
              "a": 0.5,
              "frac_le_a": 0.5207373271889401,
              "bound": 0.536001152055299,
              "pass": true
            }
          ]
        },
        "high_rul": {
          "n": 11669,
          "status": "ok",
          "mean_p": 0.6109770970329401,
          "checks": [
            {
              "a": 0.1,
              "frac_le_a": 0.031536549832890566,
              "bound": 0.11,
              "pass": true
            },
            {
              "a": 0.2,
              "frac_le_a": 0.1263175936241323,
              "bound": 0.21110873037977074,
              "pass": true
            },
            {
              "a": 0.5,
              "frac_le_a": 0.3852943696974891,
              "bound": 0.5138859129747134,
              "pass": true
            }
          ]
        },
        "early_time": {
          "n": 4585,
          "status": "ok",
          "mean_p": 0.6932535349213375,
          "checks": [
            {
              "a": 0.1,
              "frac_le_a": 0.025081788440567066,
              "bound": 0.11329146461549156,
              "pass": true
            },
            {
              "a": 0.2,
              "frac_le_a": 0.1044711014176663,
              "bound": 0.2177219528206554,
              "pass": true
            },
            {
              "a": 0.5,
              "frac_le_a": 0.26324972737186475,
              "bound": 0.5221524410258193,
              "pass": true
            }
          ]
        },
        "mid_time": {
          "n": 4535,
          "status": "ok",
          "mean_p": 0.5761150797265344,
          "checks": [
            {
              "a": 0.1,
              "frac_le_a": 0.039470782800441015,
              "bound": 0.11336453533988959,
              "pass": true
            },
            {
              "a": 0.2,
              "frac_le_a": 0.14906284454244764,
              "bound": 0.21781938045318613,
              "pass": true
            },
            {
              "a": 0.5,
              "frac_le_a": 0.43836824696802645,
              "bound": 0.5222742255664826,
              "pass": true
            }
          ]
        },
        "late_time": {
          "n": 4576,
          "status": "fail",
          "mean_p": 0.4776986087490298,
          "checks": [
            {
              "a": 0.1,
              "frac_le_a": 0.13177447552447552,
              "bound": 0.11330452890975437,
              "pass": false
            },
            {
              "a": 0.2,
              "frac_le_a": 0.2416958041958042,
              "bound": 0.2177393718796725,
              "pass": false
            },
            {
              "a": 0.5,
              "frac_le_a": 0.5310314685314685,
              "bound": 0.5221742148495906,
              "pass": false
            }
          ]
        }
      },
      "failed_blocks": [
        "low_rul",
        "mid_rul",
        "late_time"
      ],
      "num_findings": 1,
      "findings": [
        {
          "severity": "medium",
          "type": "regime_superuniformity_failure",
          "message": "Failed blocks: ['low_rul', 'mid_rul', 'late_time']"
        }
      ]
    },
    {
      "run_dir": "C:\\Users\\micha\\zGTFinal\\outputs\\final_local_fd004_fulltopo",
      "tem_metrics_path": "C:\\Users\\micha\\zGTFinal\\outputs\\final_local_fd004_fulltopo\\tem_metrics_fd004.json",
      "audit_path": "C:\\Users\\micha\\zGTFinal\\outputs\\final_local_fd004_fulltopo\\audit_fd004.json",
      "cache_path": "C:\\Users\\micha\\zGTFinal\\outputs\\final_local_fd004_fulltopo\\audit_cache_fd004.npz",
      "use_conditional_calibration": true,
      "config": {
        "pvalue_safety_margin": 0.02,
        "calibration_bins": 8,
        "calibration_min_bin_size": 128,
        "topology_level": "full",
        "surface_topology_scope": "all"
      },
      "integrity": {
        "has_nan": false,
        "coverage_in_range": true,
        "surface_topology_ok": true
      },
      "blocks": {
        "global": {
          "n": 34092,
          "status": "ok",
          "mean_p": 0.5173318589564287,
          "checks": [
            {
              "a": 0.1,
              "frac_le_a": 0.07227502053267629,
              "bound": 0.11,
              "pass": true
            },
            {
              "a": 0.2,
              "frac_le_a": 0.16839727795377216,
              "bound": 0.21000000000000002,
              "pass": true
            },
            {
              "a": 0.5,
              "frac_le_a": 0.47896867300246393,
              "bound": 0.51,
              "pass": true
            }
          ]
        },
        "healthy_prefix": {
          "n": 26513,
          "status": "ok",
          "mean_p": 0.5358921866513812,
          "checks": [
            {
              "a": 0.1,
              "frac_le_a": 0.06740089767283974,
              "bound": 0.11,
              "pass": true
            },
            {
              "a": 0.2,
              "frac_le_a": 0.1426470033568438,
              "bound": 0.21000000000000002,
              "pass": true
            },
            {
              "a": 0.5,
              "frac_le_a": 0.4456304454418587,
              "bound": 0.51,
              "pass": true
            }
          ]
        },
        "low_rul": {
          "n": 864,
          "status": "fail",
          "mean_p": 0.31272245281986943,
          "checks": [
            {
              "a": 0.1,
              "frac_le_a": 0.2013888888888889,
              "bound": 0.13061862178478972,
              "pass": false
            },
            {
              "a": 0.2,
              "frac_le_a": 0.47337962962962965,
              "bound": 0.2408248290463863,
              "pass": false
            },
            {
              "a": 0.5,
              "frac_le_a": 0.7858796296296297,
              "bound": 0.5510310363079829,
              "pass": false
            }
          ]
        },
        "mid_rul": {
          "n": 4134,
          "status": "fail",
          "mean_p": 0.4276857544645207,
          "checks": [
            {
              "a": 0.1,
              "frac_le_a": 0.09192065795839381,
              "bound": 0.11399771907606257,
              "pass": true
            },
            {
              "a": 0.2,
              "frac_le_a": 0.2818093855829705,
              "bound": 0.2186636254347501,
              "pass": false
            },
            {
              "a": 0.5,
              "frac_le_a": 0.6279632317368167,
              "bound": 0.5233295317934376,
              "pass": false
            }
          ]
        },
        "high_rul": {
          "n": 29094,
          "status": "ok",
          "mean_p": 0.5361460310493528,
          "checks": [
            {
              "a": 0.1,
              "frac_le_a": 0.06564927476455626,
              "bound": 0.11,
              "pass": true
            },
            {
              "a": 0.2,
              "frac_le_a": 0.1432254073004743,
              "bound": 0.21000000000000002,
              "pass": true
            },
            {
              "a": 0.5,
              "frac_le_a": 0.44868357736990444,
              "bound": 0.51,
              "pass": true
            }
          ]
        },
        "early_time": {
          "n": 11421,
          "status": "ok",
          "mean_p": 0.5717599491870249,
          "checks": [
            {
              "a": 0.1,
              "frac_le_a": 0.03309692671394799,
              "bound": 0.11,
              "pass": true
            },
            {
              "a": 0.2,
              "frac_le_a": 0.08817091323001489,
              "bound": 0.21122869228088692,
              "pass": true
            },
            {
              "a": 0.5,
              "frac_le_a": 0.40005253480430786,
              "bound": 0.5140358653511087,
              "pass": true
            }
          ]
        },
        "mid_time": {
          "n": 11283,
          "status": "ok",
          "mean_p": 0.5258651270643382,
          "checks": [
            {
              "a": 0.1,
              "frac_le_a": 0.07108038642205088,
              "bound": 0.11,
              "pass": true
            },
            {
              "a": 0.2,
              "frac_le_a": 0.15607551183195958,
              "bound": 0.21129715147641162,
              "pass": true
            },
            {
              "a": 0.5,
              "frac_le_a": 0.45519808561552777,
              "bound": 0.5141214393455145,
              "pass": true
            }
          ]
        },
        "late_time": {
          "n": 11388,
          "status": "fail",
          "mean_p": 0.45429145830792317,
          "checks": [
            {
              "a": 0.1,
              "frac_le_a": 0.11275026343519494,
              "bound": 0.11,
              "pass": false
            },
            {
              "a": 0.2,
              "frac_le_a": 0.26106427818756583,
              "bound": 0.2112449496918475,
              "pass": false
            },
            {
              "a": 0.5,
              "frac_le_a": 0.5816649104320337,
              "bound": 0.5140561871148094,
              "pass": false
            }
          ]
        }
      },
      "failed_blocks": [
        "low_rul",
        "mid_rul",
        "late_time"
      ],
      "num_findings": 1,
      "findings": [
        {
          "severity": "medium",
          "type": "regime_superuniformity_failure",
          "message": "Failed blocks: ['low_rul', 'mid_rul', 'late_time']"
        }
      ]
    }
  ]
}